pyjsonmodels/__init__.py
pyjsonmodels/builders.py
pyjsonmodels/collections.py
pyjsonmodels/errors.py
pyjsonmodels/fields.py
pyjsonmodels/models.py
pyjsonmodels/parsers.py
pyjsonmodels/utilities.py
pyjsonmodels/validators.py
pyjsonmodels-2.4.dist-info/DESCRIPTION.rst
pyjsonmodels-2.4.dist-info/METADATA
pyjsonmodels-2.4.dist-info/RECORD
pyjsonmodels-2.4.dist-info/WHEEL
pyjsonmodels-2.4.dist-info/metadata.json
pyjsonmodels-2.4.dist-info/top_level.txt
