Metadata-Version: 2.0
Name: pyjsonmodels
Version: 2.4
Summary: 方便处理模型转换的工具
Home-page: https://gitee.com/huichengip_chenxf/jsonmodels.git
Author: x-debug
Author-email: chenxf@partnerch.com
License: BSD
Keywords: pyjsonmodels
Platform: UNKNOWN
Classifier: Intended Audience :: Developers
Classifier: License :: OSI Approved :: BSD License
Classifier: Natural Language :: English
Classifier: Programming Language :: Python :: 2
Classifier: Programming Language :: Python :: 2.7
Classifier: Programming Language :: Python :: 3
Classifier: Programming Language :: Python :: 3.3
Classifier: Programming Language :: Python :: 3.4
Classifier: Programming Language :: Python :: 3.5
Classifier: Programming Language :: Python :: 3.6
Requires-Dist: python-dateutil
Requires-Dist: six
